demo/migrations/0001_initial.py
demo/migrations/0002_auto_20190702_1910.py
demo/migrations/__init__.py
demo/tests/__init__.py
demo/tests/common.py
demo/tests/tests_concepts.py
demo/tests/tests_importer.py
demo/tests/tests_languages.py
demo/tests/tests_rest.py
demo/tests/tests_static.py
django_ontology/__init__.py
django_ontology/admin.py
django_ontology/apps.py
django_ontology/library.py
django_ontology/models.py
django_ontology/settings.py
django_ontology/static.py
django_ontology/tests.py
django_ontology/urls.py
django_ontology/utils.py
django_ontology/views.py
django_ontology/api/__init__.py
django_ontology/api/api_queries.py
django_ontology/api/importer.py
django_ontology/api/excel/__init__.py
django_ontology/api/excel/columns.py
django_ontology/api/excel/urls.py
django_ontology/api/excel/views.py
django_ontology/api/excel/workbook.py
django_ontology/api/excel/worksheet.py
django_ontology/api/rest/__init__.py
django_ontology/api/rest/serializers.py
django_ontology/api/rest/urls.py
django_ontology/api/rest/viewsets.py
django_ontology/migrations/0001_initial.py
django_ontology/migrations/__init__.py
django_ontology/templates/django_ontology/api/excel/excel_index.html
django_ontology/templates/django_ontology/api/excel/excel_upload.html
django_ontology/templatetags/__init__.py
django_ontology/templatetags/django_ontology.py
django_ontology-0.1.21.dist-info/METADATA
django_ontology-0.1.21.dist-info/WHEEL
django_ontology-0.1.21.dist-info/top_level.txt
django_ontology-0.1.21.dist-info/RECORD
