Metadata-Version: 2.1
Name: django-ontology
Version: 0.1.21
Summary: Database based translations for django
Home-page: UNKNOWN
Author: Sverker Jerremalm
Author-email: UNKNOWN
License: MIT
Platform: UNKNOWN
Classifier: Development Status :: 3 - Alpha
Classifier: License :: OSI Approved :: MIT License
Classifier: Programming Language :: Python
Requires-Dist: django
Requires-Dist: django-model-utils
Requires-Dist: django-mptt
Requires-Dist: djangorestframework
Requires-Dist: djangorestframework-recursive
Requires-Dist: fortnum
Requires-Dist: openpyxl-templates
